randcsv/__init__.py
randcsv/cli.py
randcsv/data_type.py
randcsv/random_csv.py
randcsv/value_generators.py
tests/__init__.py
tests/test_cli.py
tests/test_data_type.py
tests/test_generate_functions.py
tests/test_random_csv.py
randcsv-0.1.3.dist-info/METADATA
randcsv-0.1.3.dist-info/WHEEL
randcsv-0.1.3.dist-info/entry_points.txt
randcsv-0.1.3.dist-info/top_level.txt
randcsv-0.1.3.dist-info/RECORD
