Metadata-Version: 2.1
Name: randcsv
Version: 0.1.3
Summary: Generate random CSVs.
Home-page: https://github.com/scriptloom/randcsv
Author: James W. Spears
Author-email: james.w.spears@gmail.com
License: UNKNOWN
Platform: UNKNOWN
Classifier: Programming Language :: Python :: 3
Classifier: License :: OSI Approved :: MIT License
Classifier: Operating System :: OS Independent
Requires-Python: >=3.6
